CHANGES.rst
CONTRIBUTORS.rst
DEVELOP.rst
LICENSE.rst
MANIFEST.in
README.rst
setup.cfg
setup.py
docs/conf.py
docs/index.rst
src/collective/__init__.py
src/collective.gnd.egg-info/PKG-INFO
src/collective.gnd.egg-info/SOURCES.txt
src/collective.gnd.egg-info/dependency_links.txt
src/collective.gnd.egg-info/entry_points.txt
src/collective.gnd.egg-info/namespace_packages.txt
src/collective.gnd.egg-info/not-zip-safe
src/collective.gnd.egg-info/requires.txt
src/collective.gnd.egg-info/top_level.txt
src/collective/gnd/__init__.py
src/collective/gnd/configure.zcml
src/collective/gnd/interfaces.py
src/collective/gnd/permissions.zcml
src/collective/gnd/setuphandlers.py
src/collective/gnd/testing.py
src/collective/gnd/upgrades.py
src/collective/gnd/upgrades.zcml
src/collective/gnd/behaviors/__init__.py
src/collective/gnd/behaviors/configure.zcml
src/collective/gnd/behaviors/gnd_id.py
src/collective/gnd/browser/__init__.py
src/collective/gnd/browser/configure.zcml
src/collective/gnd/browser/overrides/.gitkeep
src/collective/gnd/browser/static/.gitkeep
src/collective/gnd/controlpanels/__init__.py
src/collective/gnd/controlpanels/configure.zcml
src/collective/gnd/controlpanels/gnd_settings.py
src/collective/gnd/locales/README.rst
src/collective/gnd/locales/__init__.py
src/collective/gnd/locales/collective.gnd.pot
src/collective/gnd/locales/update.py
src/collective/gnd/locales/update.sh
src/collective/gnd/locales/en/LC_MESSAGES/collective.gnd.po
src/collective/gnd/profiles/default/browserlayer.xml
src/collective/gnd/profiles/default/catalog.xml
src/collective/gnd/profiles/default/controlpanel.xml
src/collective/gnd/profiles/default/metadata.xml
src/collective/gnd/profiles/default/registry.xml
src/collective/gnd/profiles/default/rolemap.xml
src/collective/gnd/profiles/uninstall/browserlayer.xml
src/collective/gnd/tests/__init__.py
src/collective/gnd/tests/test_behavior_gnd_id.py
src/collective/gnd/tests/test_robot.py
src/collective/gnd/tests/test_setup.py
src/collective/gnd/tests/test_view_beacon_gnd.py
src/collective/gnd/tests/test_view_resolvegnd.py
src/collective/gnd/tests/robot/test_example.robot
src/collective/gnd/views/__init__.py
src/collective/gnd/views/beacon_gnd.py
src/collective/gnd/views/configure.zcml
src/collective/gnd/views/gnd_resolver.py