Metadata-Version: 2.1
Name: collective.gnd
Version: 1.0
Summary: Plone addon which provides a GND resolver and a BEACON API.
Home-page: https://github.com/collective/collective.gnd
Author: Maik Derstappen
Author-email: md@derico.de
License: GPL version 2
Project-URL: Source, https://github.com/collective/collective.gnd
Project-URL: Tracker, https://github.com/collective/collective.gnd/issues
Project-URL: PyPI, https://pypi.python.org/pypi/collective.gnd
Keywords: Python Plone
Platform: UNKNOWN
Classifier: Environment :: Web Environment
Classifier: Framework :: Plone
Classifier: Framework :: Plone :: Addon
Classifier: Framework :: Plone :: 5.2
Classifier: Programming Language :: Python
Classifier: Programming Language :: Python :: 2.7
Classifier: Programming Language :: Python :: 3.6
Classifier: Programming Language :: Python :: 3.7
Classifier: Operating System :: OS Independent
Classifier: License :: OSI Approved :: GNU General Public License v2 (GPLv2)
Requires-Python: ==2.7, >=3.6
Provides-Extra: test
